LICENSE
MANIFEST.in
README.md
setup.py
wfrppy/__init__.py
wfrppy.egg-info/PKG-INFO
wfrppy.egg-info/SOURCES.txt
wfrppy.egg-info/dependency_links.txt
wfrppy.egg-info/entry_points.txt
wfrppy.egg-info/top_level.txt
wfrppy/bin/__init__.py
wfrppy/bin/frpc.bat
wfrppy/bin/frpc.exe
wfrppy/bin/frpc_task_template.xml
wfrppy/bin/frps.bat
wfrppy/bin/frps.exe
wfrppy/bin/frps_task_template.xml
wfrppy/core/__init__.py
wfrppy/core/cli.py
wfrppy/core/config_ops.py
wfrppy/core/entrypoints.py
wfrppy/core/listing.py
wfrppy/core/registry.py
wfrppy/core/tasks.py
wfrppy/core/winsvc.py
wfrppy/frpc/__init__.py
wfrppy/frpc/_shared.py
wfrppy/frpc/cleanup.py
wfrppy/frpc/deploy.py
wfrppy/frpc/file_ops.py
wfrppy/frpc/listing.py
wfrppy/frpc/pwd.py
wfrppy/frpc/service.py
wfrppy/frpc/tasks.py
wfrppy/frps/__init__.py
wfrppy/frps/_shared.py
wfrppy/frps/cleanup.py
wfrppy/frps/deploy.py
wfrppy/frps/file_ops.py
wfrppy/frps/listing.py
wfrppy/frps/pwd.py
wfrppy/frps/service.py
wfrppy/frps/tasks.py
wfrppy/resources/__init__.py
wfrppy/resources/__pycache__/__init__.cpython-312.pyc
wfrppy/resources/frpc/main.toml
wfrppy/resources/frps/main.toml