Metadata-Version: 2.4
Name: wfrppy
Version: 0.0.8
Summary: Windows 平台的 FRP 服务管理工具
Author: Cai Jianping
Author-email: jpingcai@163.com
License: MIT Licence
Keywords: frp,service,windows
Platform: any
License-File: LICENSE
Dynamic: author
Dynamic: author-email
Dynamic: description
Dynamic: keywords
Dynamic: license
Dynamic: license-file
Dynamic: platform
Dynamic: summary
